LICENSE
README.md
setup.py
sunyata/__init__.py
sunyata/cache_wrap.py
sunyata/compress.py
sunyata/concurrent.py
sunyata/consul.py
sunyata/db.py
sunyata/etcd.py
sunyata/eventloop.py
sunyata/log.py
sunyata/orm.py
sunyata/redislock.py
sunyata/table_writer.py
sunyata/util.py
sunyata/wrap.py
sunyata.egg-info/PKG-INFO
sunyata.egg-info/SOURCES.txt
sunyata.egg-info/dependency_links.txt
sunyata.egg-info/entry_points.txt
sunyata.egg-info/requires.txt
sunyata.egg-info/top_level.txt
sunyata/algorithm/__init__.py
sunyata/algorithm/avlsearchtree.py
sunyata/algorithm/avltree.py
sunyata/algorithm/binsearchtree.py
sunyata/algorithm/bintree.py
sunyata/algorithm/bloomfilter.py
sunyata/algorithm/bplustree.py
sunyata/algorithm/btree.py
sunyata/algorithm/hashtable.py
sunyata/algorithm/lru.py
sunyata/algorithm/rbtree.py
sunyata/algorithm/trie.py
sunyata/cli/__init__.py
sunyata/cli/cli.py
sunyata/cli/entry.py
sunyata/http/__init__.py
sunyata/http/factory.py
sunyata/http/middleware.py
sunyata/http/rawserver.py
sunyata/http/request.py
sunyata/http/request_stream.py
sunyata/http/response.py
sunyata/http/router.py
sunyata/http/server.py
sunyata/http/status.py
sunyata/http/transport.py
sunyata/rpc/__init__.py
sunyata/rpc/client.py
sunyata/rpc/compress.py
sunyata/rpc/const.py
sunyata/rpc/discovery.py
sunyata/rpc/encrypt.py
sunyata/rpc/exception.py
sunyata/rpc/method.py
sunyata/rpc/protocal.py
sunyata/rpc/serialize.py
sunyata/rpc/server.py
sunyata/rpc/transport.py