Metadata-Version: 2.1
Name: sunyata
Version: 0.0.47
Summary: Light, simple, asynchronous RPC framework for Python
Home-page: UNKNOWN
Author: tank
License: MIT
Keywords: sunyata
Platform: any
Classifier: Programming Language :: Python :: 3.7
Classifier: Programming Language :: Python :: 3.8
Classifier: Programming Language :: Python :: 3.9
Classifier: Programming Language :: Python :: 3.10
Classifier: Programming Language :: Python :: 3.11
Classifier: Programming Language :: Python :: 3.12
License-File: LICENSE
